eigen_robotics/__init__.py
eigen_robotics-0.1.10.dist-info/WHEEL
eigen_robotics-0.1.10.dist-info/METADATA
eigen_robotics-0.1.10.dist-info/RECORD
