Metadata-Version: 2.3
Name: eigen-robotics
Version: 0.1.10
Summary: Add your description here
Author: Sarthak Das
Author-email: Sarthak Das <sdas@icloud.com>
Requires-Dist: eigen-alia ; extra == 'alia'
Requires-Dist: eigen-framework[default] ; extra == 'default'
Requires-Dist: eigen-ml[jupyter] ; extra == 'default'
Requires-Dist: eigen-robotics[sensors,robots,alia] ; extra == 'default'
Requires-Dist: eigen-ml ; extra == 'ml'
Requires-Dist: eigen-framework[pybullet] ; extra == 'pybullet'
Requires-Dist: eigen-robots ; extra == 'robots'
Requires-Dist: eigen-sensors ; extra == 'sensors'
Requires-Python: ==3.11.*
Project-URL: Homepage, https://github.com/Eigen-Robotics/Eigen-Robotics
Project-URL: Issues, https://github.com/Eigen-Robotics/Eigen-Robotics/issues
Project-URL: Repository, https://github.com/Eigen-Robotics/Eigen-Robotics
Provides-Extra: alia
Provides-Extra: default
Provides-Extra: ml
Provides-Extra: pybullet
Provides-Extra: robots
Provides-Extra: sensors
